riskoptima/__init__.py
riskoptima/backtest/__init__.py
riskoptima/backtest/engine.py
riskoptima/backtest/portfolio.py
riskoptima/backtest/strategy.py
riskoptima/core/__init__.py
riskoptima/core/types.py
riskoptima/data/__init__.py
riskoptima/optim/__init__.py
riskoptima/optim/constraints.py
riskoptima/optim/costs.py
riskoptima/optim/mean_variance.py
riskoptima/risk/__init__.py
riskoptima/risk/factor_model.py
riskoptima/riskoptima.py
riskoptima-2.2.0.dist-info/LICENSE
riskoptima-2.2.0.dist-info/METADATA
riskoptima-2.2.0.dist-info/WHEEL
riskoptima-2.2.0.dist-info/RECORD
