Metadata-Version: 2.1
Name: riskoptima
Version: 2.2.0
Summary: RiskOptima is a powerful Python toolkit for financial risk analysis, portfolio optimization, and advanced quantitative modeling. It integrates state-of-the-art methodologies, including Monte Carlo simulations, Value at Risk (VaR), Conditional VaR (CVaR), Black-Scholes, Heston, and Merton Jump Diffusion models, to aid investors in making data-driven investment decisions.
Home-page: https://github.com/JordiCorbilla/RiskOptima
License: MIT
Keywords: portfolio,risk,optimization,VaR,CVaR,backtesting,monte-carlo,machine-learning,random-forest,linear-regression,gradient-boosting,mean-variance,black-litterman,stochastic-volatility,option-pricing,black-scholes,heston-model,merton-jump-diffusion,correlation  matrix,efficient-frontier,financial-modeling,quantitative-finance,Hull-White,Heston,SABR
Author: Jordi Corbilla
Author-email: jordi.coll.corbilla@gmail.com
Requires-Python: >=3.11
Classifier: License :: OSI Approved :: MIT License
Classifier: Programming Language :: Python :: 3
Classifier: Programming Language :: Python :: 3.11
Classifier: Programming Language :: Python :: 3.12
Classifier: Programming Language :: Python :: 3.13
Requires-Dist: matplotlib (>=3.8.4)
Requires-Dist: numpy (>=1.26.4)
Requires-Dist: pandas (>=2.1.4)
Requires-Dist: scikit-learn (>=1.5.1)
Requires-Dist: scipy (>=1.13.1)
Requires-Dist: seaborn (>=0.13.2)
Requires-Dist: squarify (>=0.4.4)
Requires-Dist: statsmodels (>=0.14.2)
Requires-Dist: xgboost (>=2.1.3)
Requires-Dist: yfinance (>=0.2.54)
Project-URL: Repository, https://github.com/JordiCorbilla/RiskOptima
